{"novel",{"article_num":"312","author":"T\u00ecnh Kh\u00f4ng Lam H\u1ec1","category_id":"4","crawl_times":null,"created_at":null,"description":"    \u00c1nh Ho\u00e0ng H\u00f4n M\u1ecfng Manh l\u00e0 m\u1ed9t truy\u1ec7n ng\u00f4n t\u00ecnh kh\u00e1 hay c\u1ee7a t\u00e1c gi\u1ea3 T\u00ecnh Kh\u00f4ng Lam H\u1ec1 m\u00e0 m\u00ecnh mu\u1ed1n gi\u1edbi thi\u1ec7u cho c\u00e1c b\u1ea1n tr\u00ean website \u0111\u1ecdc truy\u1ec7n online .\n    Tr\u00ean th\u1ebf gi\u1edbi n\u00e0y, c\u00f3 m\u1ed9t s\u1ed1 th\u1ee9 kh\u00f4ng ph\u1ea3i l\u00e0 ch\u00e2n l\u00fd nh\u01b0ng ch\u00fang ta v\u1eabn c\u1ee9 tin m\u00e0 kh\u00f4ng ch\u00fat ho\u00e0i nghi.\n    V\u00ed nh\u01b0 ng\u01b0\u1eddi ta hay n\u00f3i: \"t\u00ecnh y\u00eau kh\u00f4ng \u0111\u01b0\u1ee3c d\u1ed1i tr\u00e1\u201d. Th\u1ebf m\u00e0 anh \u0111\u00e3 l\u1eeba d\u1ed1i c\u00f4, c\u1ee9 nh\u01b0 th\u1ebf m\u1ed9t l\u1ea7n r\u1ed3i hai l\u1ea7n, nh\u01b0ng cu\u1ed1i c\u00f9ng c\u00f4 \u0111\u00e3 ph\u00e1t hi\u1ec7n ra, ng\u01b0\u1eddi n\u00f3i d\u1ed1i nhi\u1ec1u nh\u1ea5t l\u1ea1i ch\u00ednh l\u00e0 c\u00f4.\n    V\u00ed nh\u01b0: \"t\u00ecnh y\u00eau th\u00ec kh\u00f4ng th\u1ec3 song h\u00e0nh c\u00f9ng th\u00f9 h\u1eadn\u201d nh\u01b0ng c\u00f4 l\u1ea1i h\u1eadn anh. T\u1eeb \u0111\u1ea7u \u0111\u1ebfn cu\u1ed1i, v\u1eabn nh\u01b0 v\u1eady. V\u00e0 cu\u1ed1i c\u00f9ng, c\u00f4 qu\u00ean m\u1ea5t m\u1ed9t \u0111i\u1ec1u r\u1eb1ng, ch\u00ednh s\u1ef1 th\u00f9 h\u1eadn \u0111\u00f3 \u0111\u00e3 \u0111\u01b0a c\u00f4 \u0111\u1ebfn b\u00ean anh.\n    L\u1ea1i nh\u01b0: \"c\u00f3 m\u1ed9t ng\u01b0\u1eddi t\u1ed3n t\u1ea1i v\u00ec m\u1ed9t ng\u01b0\u1eddi kh\u00e1c, ch\u1eb3ng c\u1ea7n ph\u1ea3i t\u00ecm r\u1ed1t cu\u1ed9c v\u1eabn g\u1eb7p \u0111\u01b0\u1ee3c ng\u01b0\u1eddi \u1ea5y\u201d. Cho n\u00ean, s\u1ed1 ph\u1eadn \u0111\u00e3 bu\u1ed9c h\u1ecd ph\u1ea3i y\u00eau nhau, cho d\u00f9 gi\u1eefa h\u1ecd c\u00f3 mu\u00f4n ng\u00e0n c\u00e1ch tr\u1edf.\n    \u0110\u00e2y kh\u00f4ng ph\u1ea3i l\u00e0 m\u1ed9t c\u00e2u chuy\u1ec7n v\u1ec1 gi\u1edbi x\u00e3 h\u1ed9i \u0111en, c\u0169ng kh\u00f4ng ph\u1ea3i l\u00e0 c\u00e2u chuy\u1ec7n v\u1ec1 l\u00f2ng th\u00f9 h\u1eadn c\u00e0ng kh\u00f4ng ph\u1ea3i l\u00e0 nh\u1eefng d\u00f2ng ghi ch\u00e9p v\u1ec1 n\u1ed7i \u00e2n h\u1eadn, gi\u00e0y v\u00f2 \u0111\u00e2y l\u00e0 m\u1ed9t cu\u1ed1n s\u00e1ch vi\u1ebft v\u1ec1 t\u00ecnh y\u00eau.\n    M\u1ed9t \u0111\u00f4i nam n\u1eef c\u00f9ng l\u1ee3i d\u1ee5ng nhau.\n    M\u1ed9t m\u1ed1i quan h\u1ec7 \u0111\u1ea7y nh\u1eefng r\u1eafp t\u00e2m.\n    V\u00e0 m\u1ed9t t\u00ecnh y\u00eau kh\u00f4ng c\u00f3 l\u1ed1i tho\u00e1t...\n    N\u1eef nh\u00e0 b\u00e1o Ph\u01b0\u01a1ng Th\u1ea7n xinh \u0111\u1eb9p c\u1ee7a m\u1ed9t t\u00f2a b\u00e1o n\u1ecd trong m\u1ed9t l\u1ea7n t\u00ecnh c\u1edd \u0111\u00e3 quen bi\u1ebft v\u1edbi H\u00e0n Du\u1ec7, m\u1ed9t ng\u01b0\u1eddi \u0111\u00e0n \u00f4ng l\u1ea1nh l\u00f9ng, b\u00ed hi\u1ec3m, c\u00f3 xu\u1ea5t th\u00e2n l\u00e0 m\u1ed9t nh\u00e2n v\u1eadt c\u1ee7a x\u00e3 h\u1ed9i \u0111en. Sau m\u1ed9t v\u00e0i l\u1ea7n ti\u1ebfp x\u00fac, Ph\u01b0\u01a1ng Th\u1ea7n nghi ng\u1edd H\u00e0n Du\u1ec7 c\u00f3 li\u00ean quan \u0111\u1ebfn c\u00e1i ch\u1ebft ngo\u00e0i \u00fd mu\u1ed1n c\u1ee7a ch\u1ecb g\u00e1i m\u00ecnh m\u1ea5y n\u0103m tr\u01b0\u1edbc. V\u00ec th\u1ebf, c\u00f4 t\u00ecm c\u00e1ch ti\u1ebfp c\u1eadn v\u1edbi anh h\u00f2ng mong t\u00ecm ra nguy\u00ean nh\u00e2n ch\u00ednh g\u00e2y n\u00ean c\u00e1i ch\u1ebft c\u1ee7a ch\u1ecb g\u00e1i.\n    Th\u1ebf nh\u01b0ng, sau th\u1eddi gian \u1edf b\u00ean anh, sau nhi\u1ec1u s\u1ef1 vi\u1ec7c c\u00f9ng tr\u1ea3i qua v\u1edbi anh, Ph\u01b0\u01a1ng Th\u1ea7n ph\u00e1t hi\u1ec7n ra r\u1eb1ng, c\u00f4 \u0111\u00e3 d\u1ea7n d\u1ea7n y\u00eau ng\u01b0\u1eddi \u0111\u00e0n \u00f4ng \u0111\u1ea7y b\u00ed hi\u1ec3m n\u00e0y. \u0110\u00fang l\u00fac x\u00e1c nh\u1eadn \u0111\u01b0\u1ee3c t\u00ecnh c\u1ea3m c\u1ee7a m\u00ecnh th\u00ec Ph\u01b0\u01a1ng Th\u1ea7n \u0111\u01b0\u1ee3c bi\u1ebft, H\u00e0n Du\u1ec7 ch\u00ednh l\u00e0 hung th\u1ee7 \u0111\u00e3 gi\u1ebft ch\u1ebft ch\u1ecb g\u00e1i c\u00f4. Li\u1ec7u \u0111\u00e2y c\u00f3 ph\u1ea3i l\u00e0 m\u1ed9t th\u00f4ng tin ch\u00ednh x\u00e1c hay l\u00e0 m\u1ed9t \u00e2m m\u01b0u?\n    M\u1ed9t m\u1ed1i t\u00ecnh b\u1eaft \u0111\u1ea7u t\u1eeb h\u1eadn th\u00f9. C\u00f4 \u0111\u00e3 \u0111\u1ebfn b\u00ean anh c\u00f9ng v\u1edbi m\u1ed1i c\u0103m h\u1eadn, v\u00e0 b\u1ecb anh d\u00e0nh cho th\u1ee9 thu\u1ed1c \u0111\u1ed9c \u0111\u1ea7y y\u00eau th\u01b0\u01a1ng. C\u00f4 n\u00ean ti\u1ebfp t\u1ee5c y\u00eau hay ti\u1ebfp t\u1ee5c h\u1eadn th\u00f9?\n    Ph\u01b0\u01a1ng Th\u1ea7n r\u1ea5t mu\u1ed1n ng\u1ee7, kh\u00f4ng ph\u1ea3i b\u1edfi v\u00ec c\u00f4 m\u1ec7t m\u1ecfi, m\u00e0 l\u00e0 v\u00ec c\u00f4 mu\u1ed1n n\u1eb1m m\u01a1.\n    Ph\u01b0\u01a1ng Th\u1ea7n mu\u1ed1n n\u1eb1m m\u01a1 th\u1ea5y H\u00e0n Du\u1ec7, d\u00f9 ch\u1ec9 m\u1ed9t l\u1ea7n c\u0169ng \u0111\u01b0\u1ee3c.\n    Th\u1ebf nh\u01b0ng trong gi\u1ea5c ng\u1ee7, c\u00f4 kh\u00f4ng th\u1ec3 g\u1eb7p \u0111\u01b0\u1ee3c con ng\u01b0\u1eddi \u0111\u00e3 t\u1eebng \u0111\u1ec3 l\u1ea1i \u1ea5n t\u01b0\u1ee3ng s\u00e2u s\u1eafc trong cu\u1ed9c \u0111\u1eddi c\u00f4. D\u01b0\u1eddng nh\u01b0 anh anh \u0111\u00e3 h\u00f2a v\u00e0o \u00e1nh l\u1eeda ng\u00fat tr\u1eddi \u1ea5y, bi\u1ebfn m\u1ea5t ngay trong \u0111\u00eam \u1ea5y.\n    V\u00e0 c\u1ea3 trong gi\u1ea5c m\u01a1 c\u1ee7a c\u00f4 n\u1eefa.\n    Anh \u0111\u00e3 r\u1eddi xa c\u00f4 r\u1ed3i\u2026\n    M\u1eddi b\u1ea1n c\u00f9ng \u0111\u1ecdc full truy\u1ec7n \u0111\u1ec3 c\u1ea3m nh\u1eadn. Ngo\u00e0i ra b\u1ea1n c\u0169ng c\u00f3 th\u1ec3 \u0111\u1ecdc th\u00eam cu\u1ed1n N\u00e9t C\u01b0\u1eddi N\u01a1i \u1ea4y c\u0169ng r\u1ea5t hay.\n","id":"312","is_category_hot":false,"is_category_recommend":false,"is_category_this_week_hot":false,"is_classic":null,"is_classic_action":null,"is_serializing":false,"is_show":true,"last_update":"04-11-2016","link":"http:\/\/cuongtruyen.com\/truyen\/anh-hoang-hon-mong-manh\/312.html","name":"\u00c1nh Ho\u00e0ng H\u00f4n M\u1ecfng Manh","num":"66","pic":"http:\/\/cuongtruyen.com\/images\/info\/anh-hoang-hon-mong-manh\/312.jpg","updated_at":"2016-11-04T00:45:02+08:00"}}