{"id":"2736","article_num":"2736","author":"Th\u01b0\u01a1ng Thi\u00ean B\u1ea1ch H\u1ea1c","is_serializing":false,"last_update":"08-12-2016","name":"T\u1ea1o Th\u1ea7n","pic":null,"description":"    Truy\u1ec7n xoay quanh cu\u1ed9c phi\u00eau l\u01b0u c\u1ee7a m\u1ed9t thanh thi\u1ebfu ni\u00ean tr\u00ean con \u0111\u01b0\u1eddng t\u00ecm v\u00e0 kh\u00e1m ph\u00e1 c\u00e1i \u0111\u01b0\u1ee3c g\u1ecdi l\u00e0 Tr\u00ed N\u0103ng trong m\u1ed7i con ng\u01b0\u1eddi, \u0111\u1ec3 c\u00f3 th\u1ec3 ho\u00e0n thi\u1ec7n m\u00ecnh...\n    C\u00f3 t\u00e0i tr\u00ed, n\u0103ng l\u1ef1c thi\u00ean b\u1ea9m, c\u00f9ng v\u1edbi c\u01a1 duy\u00ean tr\u1eddi ban th\u00ec t\u1ea5c c\u1ea3 m\u1ecdi vi\u1ec7c \u0111\u1ec1u c\u00f3 th\u1ec3....\n    Th\u00f4ng h\u00f3a b\u00e0nh tr\u01b0\u1edbng s\u1ed1ng kh\u00f4ng n\u1ed5i l\u00e0m sao b\u00e2y gi\u1edd? Kh\u00f4ng th\u1ec3 l\u00e0m g\u00ec kh\u00e1c h\u01a1n l\u00e0 ch\u00e9m gi\u1ebft r\u1ed3i.\n    Ch\u1ec9 c\u00f3 m\u1ed9t n\u1eeda trung h\u1ecdc v\u0103n h\u00f3a \u0111\u1ecba ti\u1ec3u b\u0129 t\u1eed tr\u1edf v\u1ec1 c\u1ed5 \u0111\u1ea1i, Kh\u00f4ng ngh\u0129 t\u1edbi ngh\u00eanh \u0111\u00f3n h\u1eafn \u0111\u1ecba kh\u00f4ng ri\u00eang c\u00f3 Huynh \u0111\u01b0\u1eddng , c\u00f2n c\u00f3 Trong ng\u1ef1c !\n    Huynh \u0111\u1ec7 v\u0103n, kh\u00f4ng NP, h\u1ec9 k\u1ecbch, th\u00edch \u0111\u1ecba nh\u1ea3y h\u00e3m h\u1ea1i, nh\u1eafn l\u1ea1i, \u0111\u00e1nh ph\u00e2n, c\u1ea5t d\u1ea5u! V\u1ed1n chuy\u1ec7n x\u01b0a ch\u1ec9 do YY, nh\u01b0 c\u00f3 l\u00f4i \u0111\u1ed3ng, ch\u1ec9 do g\u1eb7p qu\u1ef7!\n    Ngu\u1ed3n: banlong\n","category_id":"8"}