{"novel",{"article_num":"2274","author":"\u0110\u1ed9c C\u00f4 H\u1ed3ng","category_id":"2","crawl_times":null,"created_at":null,"description":"    S\u01b0u t\u1ea7m\n    Gi\u1edbi thi\u1ec7u:\n    Nghe \u00f4ng ch\u00e1u c\u00e0u nh\u00e0u v\u1edbi nhau nh\u01b0 v\u1eady, L\u00e2m \u0110o\u00e0n Ngh\u0129a s\u1ef1c ngh\u0129 \u0111\u1ebfn c\u1ea3nh \u0111\u1ea7m \u1ea5m vui v\u1ea7y c\u1ee7a m\u00ecnh tr\u01b0\u1edbc \u0111\u00e2y nay ho\u00e0n to\u00e0n b\u1ecb th\u1ea3m t\u1eed, c\u00f2n bao gi\u1edd t\u00ecm \u0111\u01b0\u1ee3c nh\u1eefng ng\u00e0y vui nh\u01b0 v\u1eady n\u1eefa?\n    Ngh\u0129 t\u1edbi \u0111\u00f3 t\u1ef1 d\u01b0ng n\u01b0\u1edbc m\u1eaft tr\u00e0o ra.\n    L\u00e1t sau m\u1ed9t thi\u1ebfu n\u1eef tay x\u00e1ch \u0111\u00e8n l\u1ed3ng b\u01b0\u1edbc ra kh\u1ecfi nh\u00e0 ch\u1eadm r\u00e3i h\u01b0\u1edbng ra c\u1ed5ng theo sau c\u00f2n c\u00f3 m\u1ed9t ti\u1ec3u \u0111\u1ed3ng.\n    Ra t\u1edbi c\u1ed5ng ti\u1ec3u \u0111\u1ed3ng qu\u00e1t h\u1ecfi :\n    - Ng\u01b0\u01a1i t\u1edbi \u0111\u00e2y l\u00e0m g\u00ec?\n    Nh\u01b0ng v\u1eabn ch\u01b0a ch\u1ecbu m\u1edf c\u1ed5ng.\n    L\u00e2m \u0110o\u00e0n Ngh\u0129a ch\u1eafp tay n\u00f3i :\n    - D\u00e1m phi\u1ec1n c\u00f4 n\u01b0\u01a1ng v\u00e0 ti\u1ec3u ca m\u1edf c\u1eeda gi\u00fap, ti\u1ec3u kh\u1ea3 l\u1ee1 \u0111\u01b0\u1eddng th\u1ea5y qu\u00fd ph\u1ee7 c\u00f2n s\u00e1ng \u0111\u00e8n n\u00ean gh\u00e9 v\u00e0o xin tr\u1ecd m\u1ed9t \u0111\u00eam kh\u00f4ng bi\u1ebft c\u00f3 g\u00ec b\u1ea5t ti\u1ec7n kh\u00f4ng?\n","id":"2274","is_category_hot":false,"is_category_recommend":false,"is_category_this_week_hot":false,"is_classic":null,"is_classic_action":null,"is_serializing":false,"is_show":true,"last_update":"08-11-2016","link":"http:\/\/cuongtruyen.com\/truyen\/phan-dien-doc-lang\/2274.html","name":"Ph\u1ea5n Di\u1ec7n \u0110\u1ed9c Lang","num":"56","pic":"http:\/\/cuongtruyen.com\/images\/info\/phan-dien-doc-lang\/2274.jpg","updated_at":"2016-11-08T13:21:39+08:00"}}