{"id":"1638","article_num":"1638","author":"\u0110\u01b0\u1eddng Ng\u1ecdc Hoa","is_serializing":false,"last_update":"05-11-2016","name":"B\u1ec9 Ng\u1ea1n Chi \u00c1i","pic":null,"description":"    Thi\u00ean gi\u1edbi v\u00e0 Ma gi\u1edbi v\u1ea1n n\u0103m tranh \u0111\u1ea5u, m\u00e2u thu\u1eabn b\u1eaft ngu\u1ed3n t\u1eeb thu\u1edf b\u1eaft \u0111\u1ea7u khai thi\u00ean l\u1eadp \u0111\u1ecba , thi\u1ebft ngh\u0129 tr\u1ea3i qua m\u1ed9t th\u1eddi gian d\u00e0i nh\u01b0 v\u1eady, c\u0169ng kh\u00f4ng th\u1ec3 ph\u00e2n th\u1eafng thua m\u00e0 k\u1ebft qu\u1ea3 mang l\u1ea1i ch\u1ec9 khi\u1ebfn l\u00ea d\u00e2n kh\u1ed5 c\u1ef1c, ch\u00fang sinh l\u1ea7m than.\n    Ch\u00ednh v\u00ec th\u1ebf,\u0111\u1ec3 ch\u1ea5m d\u1ee9t t\u1ea5t c\u1ea3 nh\u1eefng chuy\u1ec7n n\u00e0y, l\u01b0\u1ee1ng gi\u1edbi Thi\u00ean Ma quy\u1ebft \u0111\u1ecbnh li\u00ean h\u00f4n nh\u1eb1m duy tr\u00ec h\u00f2a b\u00ecnh.\n    Sau m\u1ed9t th\u00e1ng suy ngh\u0129, Thi\u00ean \u0110\u1ebf \u0111\u00e3 ph\u1ea3i c\u1eafn r\u0103ng \u0111\u1ec3 b\u1ea3o b\u1ed1i t\u00e2m can c\u1ee7a b\u1ea3n th\u00e2n l\u00e0 Nh\u1ecb c\u00f4ng ch\u00faa Nhan Ly \u0111i li\u00ean h\u00f4n. Ban \u0111\u1ea7u t\u1ea5t c\u1ea3 qu\u1ea7n th\u1ea7n \u0111\u1ec1u s\u1eedng s\u1ed1t, m\u1ed9t l\u00f2ng ph\u1ea3n \u0111\u1ed1i . H\u1ecd \u0111\u1ec1u ngh\u0129, nh\u1ecb c\u00f4ng ch\u00faa l\u00e0 m\u1ed9t n\u1eef t\u1eed to\u00e0n v\u1eb9n, ho\u00e0n m\u1ef9 nh\u1ea5t tam gi\u1edbi, l\u00e0 m\u1ed9t \u0111\u00f3a B\u1ec9 Ng\u1ea1n ki\u00eau sa nh\u1ea5t l\u1ee5c gi\u1edbi , c\u0169ng l\u00e0 m\u1ed9t ng\u01b0\u1eddi v\u00f4 c\u00f9ng \u0111\u1eb7c bi\u1ec7t khi l\u00e0 ng\u01b0\u1eddi Thi\u00ean gi\u1edbi l\u1ea1i c\u00f3 nguy\u00ean th\u00e2n l\u00e0 B\u1ec9 Ng\u1ea1n hoa, t\u01b0\u1ee3ng tr\u01b0ng c\u1ee7a Ma gi\u1edbi, tu vi ngang ng\u1eeda v\u1edbi m\u1ed9t v\u1ecb th\u01b0\u1ee3ng th\u1ea7n th\u01b0\u1ee3ng c\u1ed5, dung m\u1ea1o l\u00e0 \u0111\u1ed9c nh\u1ea5t v\u00f4 nh\u1ecb!\n    Khi c\u00f4ng ch\u00faa ch\u00e0o \u0111\u1eddi, c\u00f3 t\u1eadn hai tr\u0103m chim ng\u0169 s\u1eafc \u0111\u1ebfn bay l\u01b0\u1ee3n kh\u1eafp c\u1ea3 Thi\u00ean gi\u1edbi, ngay c\u1ea3 Thi\u00ean \u0110\u1ebf khi x\u01b0a c\u0169ng ch\u1ec9 c\u00f3 m\u1ed9t tr\u0103m n\u0103m m\u01b0\u01a1i chim ng\u0169 s\u1eafc \u0111\u1ebfn ch\u00fac m\u1eebng ,ch\u1ee9ng t\u1ecf c\u00f4ng ch\u00faa \u0111i\u1ec7n h\u1ea1 l\u00e0 \u0111i\u1ec1m may m\u1eafn, ni\u1ec1m t\u1ef1 h\u00e0o c\u1ee7a Thi\u00ean t\u1ed9c. Nh\u01b0ng ng\u1eabm l\u1ea1i, trong Thi\u00ean t\u1ed9c, ch\u1ec9 c\u00f3 nh\u1ecb c\u00f4ng ch\u00faa l\u00e0 x\u1ee9ng \u0111\u00e1ng nh\u1ea5t, d\u00f9 g\u00ec \u0111\u1ed1i ph\u01b0\u01a1ng c\u0169ng l\u00e0 m\u1ed9t nam t\u1eed xu\u1ea5t ch\u00fang .\n    C\u00f4ng ch\u00faa c\u1ee7a h\u1ecd c\u00e1i g\u00ec c\u0169ng t\u1ed1t, c\u00e1i g\u00ec c\u0169ng gi\u1ecfi, ch\u1ec9 c\u00f3 m\u1ed9t khuy\u1ebft \u0111i\u1ec3m nh\u1ecf l\u00e0 qu\u00e1 c\u1ee9ng \u0111\u1ea7u. Tuy nhi\u00ean, n\u1ebfu so n\u00e0ng v\u1edbi c\u00e1c n\u1eef t\u1eed kh\u00e1c, n\u00e0ng v\u1eabn h\u01a1n g\u1ea5p v\u1ea1n l\u1ea7n!\n    Ch\u00ednh v\u00ec c\u00f4ng ch\u00faa c\u1ee9ng \u0111\u1ea7u, n\u00ean n\u00e0o ch\u1ecbu \u0111\u00e1p \u1ee9ng \u0111i li\u00ean h\u00f4n?\n    Nh\u01b0ng \u0111\u1ed1i t\u01b0\u1ee3ng l\u1ea1i l\u00e0 m\u1ed9t Ma Qu\u00e2n .\n    Ma Qu\u00e2n v\u1ed1n \u0111\u00e3 l\u00e0 m\u1ed9t ng\u01b0\u1eddi xu\u1ea5t ch\u00fang c\u00f3 ti\u1ebfng, ngay c\u1ea3 Thi\u00ean \u0110\u1ebf x\u01b0a nay ch\u01b0a t\u1eebng khen ng\u1ee3i ai c\u0169ng kh\u00f4ng nh\u1ecbn \u0111\u01b0\u1ee3c ph\u1ea3i khen h\u1eafn m\u1ed9t ti\u1ebfng t\u00e0i hoa .\n    T\u1eed ki\u1ebfm tr\u00ean tay h\u1eafn vung l\u00ean , v\u1ea1n ng\u01b0\u1eddi bay \u0111\u1ea7u\u2026\n    S\u00e1t kh\u00ed c\u1ee7a h\u1eafn qu\u00e9t qua, v\u1ea1n ng\u01b0\u1eddi th\u1ed5 huy\u1ebft quy thi\u00ean \u2026\n    Gi\u1ebft ng\u01b0\u1eddi kh\u00f4ng ch\u1edbp m\u1eaft, l\u1ea1nh l\u00f9ng b\u00e1 \u0111\u1ea1o, nh\u00e0n t\u1ea3n thong dong, th\u1ee7 \u0111o\u1ea1n t\u00e0n nh\u1eabn ch\u00ednh l\u00e0 b\u1ea3n ch\u1ea5t c\u1ee7a Long Ph\u00e1 Nguy\u1ec7t h\u1eafn.\n    Nghe n\u00f3i, Nhan Ly \u0110\u1ebf C\u01a1  v\u1eeba nghe xong th\u00e1nh ch\u1ec9 , li\u1ec1n l\u00e0m lo\u1ea1n c\u1ea3 l\u00ean, vung tay ph\u00e1 n\u00e1t ph\u00e2n n\u1eeda v\u01b0\u1eddn Th\u01b0\u1ee3ng Uy\u1ec3n t\u00e2m \u0111\u1eafc c\u1ee7a Thi\u00ean \u0110\u1ebf.\n    V\u01b0\u01a1ng M\u1eabu n\u01b0\u01a1ng n\u01b0\u01a1ng nhi\u1ec1u l\u1ea7n khuy\u00ean b\u1ea3o , nh\u1eb9 c\u00f3 n\u1eb7ng c\u00f3 nh\u01b0ng \u0111\u1ec1u kh\u00f4ng \u0111\u01b0\u1ee3c. M\u00e0 n\u1ebfu \u0111\u1ec3 m\u1ed9t c\u00f4ng ch\u00faa kh\u00e1c \u0111i trong khi th\u00e1nh ch\u1ec9 \u0111\u00e3 ban xu\u1ed1ng, chuy\u1ec7n n\u00e0y n\u1ebfu truy\u1ec1n ra ngo\u00e0i, h\u00e1 ch\u1eb3ng ph\u1ea3i l\u00e0m m\u1ea5t th\u1ec3 di\u1ec7n c\u1ee7a Thi\u00ean t\u1ed9c sao?\n    Cu\u1ed1i c\u00f9ng, Thi\u00ean \u0110\u1ebf b\u1ea5t l\u1ef1c, V\u01b0\u01a1ng M\u1eabu b\u1ea5t l\u1ef1c, ch\u00fang ti\u00ean nh\u00e2n b\u1ea5t l\u1ef1c, \u0111\u00e0nh ph\u1ea3i d\u00f9ng \u0111\u1ebfn h\u1ea1 s\u00e1ch l\u00e0 phong \u1ea5n ti\u00ean l\u1ef1c c\u1ee7a c\u00f4ng ch\u00faa l\u1ea1i, n\u00e9m v\u00e0o ki\u1ec7u hoa , th\u1eb3ng \u0111\u1ebfn Ma Cung b\u00e1i \u0111\u01b0\u1eddng\u2026\n    B\u1ecb phong \u1ea5n ti\u00ean l\u1ef1c, n\u00e0ng v\u00f4 c\u00f9ng th\u1ed1ng kh\u1ed5. H\u01a1n th\u1ebf, phong \u1ea5n qu\u00e1i qu\u1ef7 n\u00e0y l\u1ea1i ch\u1ec9 c\u00f3 th\u1ec3 h\u00f3a gi\u1ea3i khi n\u00e0ng \u1edf Ma gi\u1edbi. C\u0169ng \u0111\u1ed3ng ngh\u0129a v\u1edbi vi\u1ec7c n\u1ebfu n\u00e0ng ra kh\u1ecfi Ma gi\u1edbi, th\u00ec c\u0169ng ch\u1eb3ng th\u1ec3 c\u01b0\u1ee1i m\u00e2y bay v\u1ec1 !\n    N\u1ebfu \u0111\u00e3 th\u1ebf, chi b\u1eb1ng\u2026 \u1edf l\u1ea1i tr\u00fat gi\u1eadn l\u00ean Ma Qu\u00e2n \u0111\u00e1ng ch\u1ebft kia, l\u00e0m h\u1eafn ch\u00e1n gh\u00e9t n\u00e0ng, \u0111u\u1ed5i n\u00e0ng v\u1ec1 r\u1ed3i ch\u1ecdn ng\u01b0\u1eddi kh\u00e1c thay th\u1ebf th\u00ec \u0111\u01b0\u1ee3c r\u1ed3i!\n    Ch\u1ec9 l\u00e0, v\u1ea1n l\u1ea7n kh\u00f4ng ng\u1edd \u0111\u1ebfn, m\u1edbi l\u00e0m t\u00e2n n\u01b0\u01a1ng ng\u01b0\u1eddi ta ch\u01b0a \u0111\u1ebfn hai ng\u00e0y, th\u00ec Y\u00eau th\u00fa B\u1ea1ch H\u00e0n , y\u00eau th\u00fa m\u1ea1nh nh\u1ea5t trong s\u1ed1 ba y\u00eau th\u00fa th\u01b0\u1ee3ng c\u1ed5 \u0111\u00e3 tho\u00e1t kh\u1ecfi phong \u1ea5n r\u1ed3i.\n    N\u1ebfu Long Ph\u00e1 Nguy\u1ec7t l\u00e0 m\u1ed9t ng\u01b0\u1eddi nh\u00e0n t\u1ea3n, thong dong, th\u1ee7 \u0111o\u1ea1n t\u00e0n nh\u1eabn th\u00ec B\u1ea1ch H\u00e0n l\u1ea1i l\u00e0 m\u1ed9t ng\u01b0\u1eddi v\u1eeba l\u1ea1nh l\u00f9ng, v\u1eeba d\u1ecbu d\u00e0ng nh\u01b0 tr\u0103ng, gi\u1ebft ng\u01b0\u1eddi kh\u00f4ng ch\u1edbp m\u1eaft, th\u1eadm ch\u00ed, cho d\u00f9 l\u00e0 ngh\u00ecn x\u00e1c ph\u01a1i \u0111\u1ea7y tr\u01b0\u1edbc m\u1eb7t, h\u1eafn c\u0169ng ch\u1ec9 nh\u1ebfch mi\u1ec7ng c\u01b0\u1eddi.\n    C\u00e0ng kh\u00f4ng ng\u1edd r\u1eb1ng, h\u1eafn l\u1ea1i l\u00e0 ng\u01b0\u1eddi m\u00e0 ta ng\u00e0y \u0111\u00eam mong ng\u00f3ng su\u1ed1t nh\u1eefng ng\u00e0y th\u00e1ng qua. H\u1eafn r\u00f5 r\u00e0ng l\u00e0 y\u00eau th\u00fa th\u01b0\u01a1ng c\u1ed5, nh\u01b0ng l\u1ea1i y\u00eau m\u1ecb \u0111\u1ebfn \u0111\u00e1ng s\u1ee3, gi\u1ed1ng nh\u01b0 ch\u1ec9 c\u1ea7n nh\u00ecn v\u00e0o th\u00ec l\u1eadp t\u1ee9c s\u1ebd b\u1ecb m\u00ea ho\u1eb7c, m\u00e3i m\u00e3i tr\u1ea7m lu\u00e2n trong \u0111\u00f3.\n    Y\u00eau th\u00fa kh\u00f4ng c\u00f3 nh\u00e2n t\u00ednh, kh\u00f4ng c\u00f3 t\u00ecnh y\u00eau.\n    Nh\u01b0ng v\u0129nh vi\u1ec5n ta c\u0169ng kh\u00f4ng th\u1ec3 hi\u1ec3u \u0111\u01b0\u1ee3c, h\u1eafn l\u1ea1i \u0111\u1ed9ng t\u00ecnh.\n    T\u00ecnh c\u1ea3m gi\u1eefa th\u1ea7n v\u00e0 th\u00fa l\u00e0 v\u0129nh vi\u1ec5n kh\u00f4ng th\u1ec3 ch\u1ea5p nh\u1eadn, v\u00ec th\u1ebf, h\u1eafn v\u00ec ta, ph\u1ea5n \u0111\u1ea5u tu luy\u1ec7n, tr\u1edf th\u00e0nh m\u1ed9t v\u1ecb th\u1ea7n, d\u00f9 v\u1eabn bi\u1ebft, t\u1eeb khi khai thi\u00ean l\u1eadp \u0111\u1ecba \u0111\u1ebfn nay, ch\u01b0a ai c\u00f3 kh\u1ea3 n\u0103ng l\u00e0m \u0111\u01b0\u1ee3c vi\u1ec7c \u0111\u00f3. C\u00f3 ng\u01b0\u1eddi b\u1ecb ch\u00ednh l\u1ef1c \u0111\u1ea1o c\u1ee7a m\u00ecnh ph\u1ea3n ph\u1ec7 m\u00e0 h\u00f4i phi y\u00ean di\u1ec7t, c\u0169ng c\u00f3 ng\u01b0\u1eddi nh\u1eadp ma.\n    R\u1ed1t cu\u1ed9c B\u1ea1ch H\u00e0n c\u00f3 th\u00e0nh c\u00f4ng hay c\u00f4ng, \u0111i\u1ec1u n\u00e0y v\u1eabn ch\u01b0a th\u1ec3 bi\u1ebft tr\u01b0\u1edbc \u0111\u01b0\u1ee3c.\n    Hai nam nh\u00e2n n\u00e0y, ta \u0111\u1ec1u c\u00f3 ch\u00fat l\u01b0u luy\u1ebfn.\n    N\u1ebfu nh\u1ea5t \u0111\u1ecbnh ph\u1ea3i ch\u1ecdn m\u1ed9t trong hai ng\u01b0\u1eddi h\u1ecd, th\u00ec h\u00e3y \u0111\u1ec3 th\u1eddi gian quy\u1ebft \u0111\u1ecbnh t\u1ea5t c\u1ea3 \u0111i!\n","category_id":"4"}