{"id":"1911","article_num":"1911","author":"Ranly","is_serializing":false,"last_update":"06-11-2016","name":"Ch\u1ed3ng \u01a0i!...Em Y\u00eau Anh Nhi\u1ec1u L\u1eafm!","pic":null,"description":"    T\u00ean Truy\u1ec7n :nbspCh\u1ed3ng \u01a0i!...Em Y\u00eau Anh Nhi\u1ec1u L\u1eafm!\n    T\u00e1c gi\u1ea3: Ranly\n    Th\u1ec3 lo\u1ea1i: Truy\u1ec7n Teen\n    T\u00ecnh tr\u1ea1ng: Ho\u00e0n Th\u00e0nh\n    Website:\n    Ngu\u1ed3n: S\u01b0u t\u1ea7m\n    Gi\u1edbi thi\u1ec7u:\n    N\u00f3 v\u00e0 Anh b\u1ecb d\u00ednh v\u00e0o h\u00f4n \u01b0\u1edbc c\u1ee7a hai gia \u0111\u00ecnh , n\u00f3 y\u00eau anh ngay t\u1eeb anh m\u1eaft \u0111\u1ea7u ti\u00ean , nh\u01b0ng anh th\u00ec lu\u00f4n ch\u1edd c\u00f4 b\u1ea1n g\u00e1i c\u1ee7a anh \u1edf b\u00ean Ph\u00e1p , kh\u00f4ng bao gi\u1edd ch\u1ea5p nh\u1eadn n\u00f3 b\u01b0\u1edbc v\u00e0o tim m\u00ecnh , tuy l\u00e0 v\u1ee3 ch\u1ed3ng , nh\u01b0ng n\u00f3 lu\u00f4n l\u00e0 ng\u01b0\u1eddi v\u00f4 h\u00ecnh \u0111\u1ed1i v\u1edbi h\u1eafn.....nbsp\n","category_id":"4"}