{"novel",{"article_num":"2416","author":"Ph\u00e1t Ti\u00eau \u0110\u00edch Oa Ng\u01b0u","category_id":"1","crawl_times":null,"created_at":null,"description":"    \u00c1nh s\u00e1ng tr\u00ed tu\u1ec7 \u0111\u1ebfn t\u1eeb thi\u00ean \u0111\u01b0\u1eddng Ng\u00e2n Di\u1ec7u.\n    Ng\u01b0\u1eddi th\u1ee7 h\u1ed9 c\u1ee7a t\u1ef1 nhi\u00ean.\n    \u0110\u00e2y l\u00e0 truy\u1ec1n k\u1ef3 v\u01b0\u01a1ng gi\u1ea3 c\u1ee7a \u0111\u1ee9c l\u1ed7 y  A Kh\u1eafc M\u00f4ng T\u01b0 .\n    Ngu\u1ed3n: bachngocsach\n","id":"2416","is_category_hot":false,"is_category_recommend":false,"is_category_this_week_hot":false,"is_classic":null,"is_classic_action":null,"is_serializing":false,"is_show":true,"last_update":"12-11-2016","link":"http:\/\/cuongtruyen.com\/truyen\/doc-tai-chi-kiem\/2416.html","name":"\u0110\u1ed9c t\u00e0i chi ki\u1ebfm","num":"15","pic":"http:\/\/cuongtruyen.com\/images\/info\/doc-tai-chi-kiem\/2416.jpg","updated_at":"2016-11-12T03:21:59+08:00"}}