{"novel",{"article_num":"503","author":"Nh\u00e2n Gian Ti\u1ec3u Kh\u1ea3","category_id":"4","crawl_times":null,"created_at":null,"description":"    Alobooks\n    >\n    M\u1edf \u0111\u1ea7u\n    \u201cY\u00eau nhau v\u00e0 Chia xa, \u0111\u1ec1u l\u00e0 l\u1ebd t\u1ea5t y\u1ebfu trong s\u1ef1 ng\u1eabu nhi\u00ean, b\u1ea5t lu\u1eadn k\u1ebft qu\u1ea3 nh\u01b0 th\u1ebf n\u00e0o, b\u1ea5t lu\u1eadn th\u1eddi gian \u0111\u00fang sai\u201d.\n    M\u1ecdi ng\u01b0\u1eddi \u0111\u1ec1u bi\u1ebft, \u0110i\u1ec1n Kh\u1ea3 L\u1ea1c l\u00e0 m\u1ed9t \u0111\u1ee9a ng\u1ed1c ngh\u1ebfch.\n    B\u00e0i to\u00e1n l\u1edbp m\u1ed9t h\u1ed5i Ti\u1ec3u h\u1ecdc, n\u00f3 m\u00e3i v\u1eabn kh\u00f4ng hi\u1ec3u r\u00f5 \u0111\u01b0\u1ee3c.\n    Th\u1ea7y d\u1ea1y to\u00e1n h\u1ecfi n\u00f3: \u201c\u0110i\u1ec1n Kh\u1ea3 L\u1ea1c, m\u1ed9t qu\u1ea3 chu\u1ed1i chia cho ba b\u1ea1n nh\u1ecf, trong \u0111\u00f3 c\u00f3 hai b\u1ea1n m\u1ed7i ng\u01b0\u1eddi \u0111\u01b0\u1ee3c m\u1ed9t n\u1eeda, b\u1ea1n th\u1ee9 ba \u0111\u01b0\u1ee3c m\u1ea5y ph\u1ea7n?\u201d\n    \u201cH\u1ebft r\u1ed3i\u201d.\n    \u201cH\u1ebft r\u1ed3i? L\u00e0 m\u1ea5y?\u201d Th\u1ef1c ch\u1ea5t th\u1ea7y gi\u00e1o mu\u1ed1n n\u00f3 tr\u1ea3 l\u1eddi l\u00e0 \u201c0 ph\u1ea7n\u201d.\n    \u0110i\u1ec1n Kh\u1ea3 L\u1ea1c ngh\u0129 m\u00e3i, tr\u1ea3 l\u1eddi ch\u1eafc ch\u1eafn r\u1eb1ng: \u201cV\u1ecf chu\u1ed1i\u201d.\n    L\u00e0m cho c\u1ea3 l\u1edbp \u0111\u01b0\u1ee3c m\u1ed9t tr\u1eadn c\u01b0\u1eddi nghi\u00eang ng\u1ea3.\n    Th\u1ea7y gi\u00e1o l\u1ea1i h\u1ecfi: \u201cN\u1ebfu em c\u00f3 ba qu\u1ea3 t\u00e1o, chia cho ba b\u1ea1n nh\u1ecf m\u1ed7i ng\u01b0\u1eddi m\u1ed9t qu\u1ea3, em c\u00f2n l\u1ea1i m\u1ea5y qu\u1ea3?\u201d\n    \u201cEm kh\u00f4ng bi\u1ebft \u1ea1!\u201d \u0110i\u1ec1n Kh\u1ea3 L\u1ea1c kh\u1ed5 s\u1edf l\u1eafc \u0111\u1ea7u.\n    \u201c\u0110i\u1ec1u n\u00e0y m\u00e0 c\u0169ng kh\u00f4ng bi\u1ebft?\u201d Th\u1ea7y gi\u00e1o b\u1eaft \u0111\u1ea7u s\u1ed1t ru\u1ed9t.\n    \u0110i\u1ec1n Kh\u1ea3 L\u1ea1c c\u0169ng cu\u1ed1ng l\u1eafm r\u1ed3i, t\u1ee7i th\u00e2n ch\u1edbp \u0111\u00f4i m\u1eaft ng\u1edd ngh\u1ec7ch, n\u00f3i khe kh\u1ebd: \u201cEm th\u1eadt ra kh\u00f4ng c\u00f3 qu\u1ea3 t\u00e1o n\u00e0o c\u1ea3, l\u00e0m sao chia cho c\u00e1c b\u1ea1n \u1ea5y \u0111\u01b0\u1ee3c?\u201d\n    \u201cSao em kh\u00f4ng ch\u1ecbu t\u01b0\u1edfng t\u01b0\u1ee3ng m\u1ed9t ch\u00fat?\u201d Th\u1ea7y gi\u00e1o c\u1ea7m th\u01b0\u1edbc k\u1ebb l\u00ean, \u0111\u1ee9ng b\u00ean c\u1ea1nh \u0110i\u1ec1n Kh\u1ea3 L\u1ea1c, nghi\u00eam ngh\u1ecb nh\u00ecn n\u00f3.\n    \u0110i\u1ec1n Kh\u1ea3 L\u1ea1c \u00f2a l\u00ean kh\u00f3c, n\u00f3i: \u201cTh\u1ea7y, l\u1ea7n tr\u01b0\u1edbc r\u00f5 r\u00e0ng th\u1ea7y ch\u1ec9 d\u00f9ng l\u00ea \u0111\u1ec3 l\u00e0m ph\u00e9p t\u00ednh, t\u1ea1i sao h\u00f4m nay l\u1ea1i c\u1ee9 \u0111\u1ed5i th\u00e0nh chu\u1ed1i v\u1edbi t\u00e1o?\u201d\n    V\u1ebb m\u1eb7t c\u1ee7a th\u1ea7y gi\u00e1o l\u00fac n\u00e0y gi\u1ed1ng nh\u01b0 \u0111ang \u2026 nu\u1ed1t ph\u1ea3i m\u1ed9t con ru\u1ed3i v\u1eady.\n    \u0110\u01b0\u1ee3c r\u1ed3i, \u0111\u1ee9a ng\u1ed1c k\u1ec3 tr\u00ean ch\u00ednh l\u00e0 t\u00f4i, t\u00f4i ch\u00ednh l\u00e0 \u0110i\u1ec1n Kh\u1ea3 L\u1ea1c.\n    Nh\u01b0ng t\u00f4i kh\u00f4ng th\u00edch ng\u01b0\u1eddi ta g\u1ecdi t\u00ean c\u1ee7a m\u00ecnh.\n    M\u1ed7i l\u1ea7n c\u00f3 ng\u01b0\u1eddi g\u1ecdi t\u00ean t\u00f4i, t\u00f4i \u0111\u1ec1u c\u1ea3m th\u1ea5y m\u00ecnh \u0111\u00fang l\u00e0 ng\u1ed1c \u0111\u1ebfn \u0111\u1ed9 n\u1ed5i bong b\u00f3ng.\n    \u00d4ng tr\u1eddi r\u1ea5t c\u00f4ng b\u1eb1ng, kh\u00f4ng cho b\u1ea1n c\u00e1i \u0111\u1ea7u th\u00f4ng minh, nh\u1ea5t \u0111\u1ecbnh s\u1ebd b\u00f9 \u0111\u1eafp cho b\u1ea1n c\u00e1i kh\u00e1c. L\u00fac ng\u00e0i Th\u01b0\u1ee3ng \u0111\u1ebf \u0111\u00f3 \u0111ang ng\u1ee7 g\u1eadt, v\u00f4 t\u00ecnh \u0111\u00e3 ban cho t\u00f4i m\u1ed9t khu\u00f4n m\u1eb7t xinh \u0111\u1eb9p. Th\u1eadm ch\u00ed t\u00f4i c\u00f2n g\u1eb7p \u00f4ng \u1ea5y trong gi\u1ea5c m\u01a1, \u00f4ng b\u1ea3o r\u1eb1ng: \u201cCon \u01a1i, h\u00e3y \u0111i \u0111i, sau n\u00e0y con s\u1ebd h\u1ea1nh ph\u00fac!\u201d\n    Nh\u01b0ng m\u00e0, h\u1ea1nh ph\u00fac c\u1ee7a con ng\u01b0\u1eddi \u0111\u00e2u c\u00f3 d\u1ec5 d\u00e0ng \u0111\u1ebfn th\u1ebf?\n    \u2014\u2014\u2014\u2014\u2014\u2014\u2014\n    Trong ti\u1ebfng H\u00e1n, ch\u1eef co-la \u0111\u01b0\u1ee3c phi\u00ean \u00e2m th\u00e0nh ch\u1eef \u201ckh\u1ea3 l\u1ea1c\u201d, cho n\u00ean, ch\u1ec9 c\u1ea7n nghe t\u00ean Kh\u1ea3 L\u1ea1c, m\u1ecdi ng\u01b0\u1eddi \u0111\u1ec1u li\u00ean t\u01b0\u1edfng ngay \u0111\u1ebfn co-la.\n    \u00d4ng tr\u1eddi r\u1ea5t c\u00f4ng b\u1eb1ng, kh\u00f4ng cho b\u1ea1n c\u00e1i \u0111\u1ea7u th\u00f4ng minh, nh\u1ea5t \u0111\u1ecbnh s\u1ebd b\u00f9 \u0111\u1eafp cho b\u1ea1n c\u00e1i kh\u00e1c. L\u00fac ng\u00e0i Th\u01b0\u1ee3ng \u0111\u1ebf \u0111\u00f3 \u0111ang ng\u1ee7 g\u1eadt, v\u00f4 t\u00ecnh \u0111\u00e3 ban cho t\u00f4i m\u1ed9t khu\u00f4n m\u1eb7t xinh \u0111\u1eb9p. Th\u1eadm ch\u00ed t\u00f4i c\u00f2n g\u1eb7p \u00f4ng \u1ea5y trong gi\u1ea5c m\u01a1, \u00f4ng b\u1ea3o r\u1eb1ng: \u201cCon \u01a1i, h\u00e3y \u0111i \u0111i, sau n\u00e0y con s\u1ebd h\u1ea1nh ph\u00fac!\u201d\n    Nh\u01b0ng m\u00e0, h\u1ea1nh ph\u00fac c\u1ee7a con ng\u01b0\u1eddi \u0111\u00e2u c\u00f3 d\u1ec5 d\u00e0ng \u0111\u1ebfn th\u1ebf?\n","id":"503","is_category_hot":false,"is_category_recommend":false,"is_category_this_week_hot":false,"is_classic":null,"is_classic_action":null,"is_serializing":false,"is_show":true,"last_update":"04-11-2016","link":"http:\/\/cuongtruyen.com\/truyen\/vut-bo-anh-la-dieu-dung-cam-nhat\/503.html","name":"V\u1ee9t B\u1ecf Anh L\u00e0 \u0110i\u1ec1u D\u0169ng C\u1ea3m Nh\u1ea5t","num":"57","pic":"http:\/\/cuongtruyen.com\/images\/info\/vut-bo-anh-la-dieu-dung-cam-nhat\/503.jpg","updated_at":"2016-11-04T06:47:43+08:00"}}