{"id":"1466","article_num":"1466","author":"Trang Trang","is_serializing":false,"last_update":"05-11-2016","name":"M\u00f9a Tuy\u1ebft R\u01a1i","pic":null,"description":"    N\u1ebfu b\u1ea1n \u0111\u00e3 t\u1eebng \u0111\u1ecdc truy\u1ec7n G\u1eb7p Em D\u01b0\u1edbi M\u01b0a Xu\u00e2n ch\u1eafc h\u1eb3n \u0111\u00e3 y\u00eau th\u00edch t\u00e1c gi\u1ea3 Trang Trang v\u00e0 mu\u1ed1n \u0111\u1ecdc nh\u1eefng t\u00e1c ph\u1ea9m c\u1ee7a c\u00f4 \u1ea5y. Theo y\u00eau c\u1ea7u c\u1ee7a m\u1ed9t s\u1ed1 b\u1ea1n h\u00f4m nay m\u00ecnh post truy\u1ec7n ng\u00f4n t\u00ecnh M\u00f9a Tuy\u1ebft R\u01a1i l\u00ean web \u0111\u1ecdc truy\u1ec7n online d\u00e0nh cho smartphone  \u0111\u1ec3 m\u1ecdi ng\u01b0\u1eddi c\u00f9ng \u0111\u1ecdc.\n    Ngay c\u1ea3 trong cu\u1ed9c s\u1ed1ng x\u00f4 b\u1ed3 v\u1eabn lu\u00f4n t\u1ed3n t\u1ea1i th\u1ee9 t\u00ecnh y\u00eau tinh khi\u1ebft nh\u01b0 nh\u1eefng b\u00f4ng tuy\u1ebft \u0111\u1ea7u m\u00f9a. \u201cM\u00f9a tuy\u1ebft r\u01a1i\u201d l\u00e0 c\u00e2u chuy\u1ec7n t\u00ecnh y\u00eau gi\u1eefa hai con ng\u01b0\u1eddi tr\u00e1i ng\u01b0\u1ee3c nhau. C\u00e2u chuy\u1ec7n c\u1ee7a h\u1ecd ch\u1ee9a \u0111\u1ea7y nh\u1eefng gi\u1eb1ng x\u00e9, day d\u1ee9t nh\u01b0ng c\u0169ng kh\u00f4ng \u00edt ng\u1ecdt ng\u00e0o, h\u1ea1nh ph\u00fac, \u0111em \u0111\u1ebfn cho \u0111\u1ed9c gi\u1ea3 nh\u1eefng chi\u00eam nghi\u1ec7m \u0111\u1ea7y \u00fd ngh\u0129a v\u1ec1 t\u00ecnh y\u00eau.\n    T\u1eed K\u1ef3, m\u1ed9t c\u00f4 g\u00e1i th\u00e0nh \u0111\u1ea1t, gi\u1ecfi giang v\u00e0 \u0111\u1ed9c l\u1eadp trong m\u1eaft m\u1ecdi ng\u01b0\u1eddi, lu\u00f4n lu\u00f4n \u0111\u01b0\u1ee3c \u0111\u00e1nh gi\u00e1 l\u00e0 ng\u01b0\u1eddi \"c\u00f3 l\u00f2ng d\u1ea1 s\u1eaft \u0111\u00e1\u201d, kh\u00f4ng nh\u1eadn l\u1eddi b\u1ea5t k\u1ef3 ai theo \u0111u\u1ed5i. Kh\u00f4ng ai bi\u1ebft \u0111\u1eb1ng sau s\u1ef1 t\u1ef1 tin \u0111\u00f3 \u1ea9n d\u1ea5u m\u1ed9t t\u00ecnh y\u00eau b\u00ed m\u1eadt m\u00e0 ch\u00ednh b\u1ea3n th\u00e2n c\u00f4 lu\u00f4n che d\u1ea5u.\n    Trong m\u1ed9t chuy\u1ebfn c\u00f4ng t\u00e1c t\u1edbi th\u00e0nh ph\u1ed1 B, c\u00f4 t\u00ecnh c\u1edd g\u1eb7p l\u1ea1i Tri\u1ec3n V\u00e2n D\u1ecbch, ng\u01b0\u1eddi \u0111\u00e0n \u00f4ng m\u00e0 c\u00f4 \u0111\u00e3 y\u00eau trong su\u1ed1t b\u1ea3y n\u0103m v\u00e0 m\u1ea5t \u0111\u1ebfn b\u1ed1n n\u0103m \u0111\u1ec3 c\u1ed1 qu\u00ean \u0111i v\u00e0 ch\u1ea1y tr\u1ed1n kh\u1ecfi nh\u1eefng k\u00fd \u1ee9c v\u1ec1 anh.\n    L\u00fac n\u00e0y \u0111\u00e2y, nh\u1eefng ng\u1ecdt ng\u00e0o, n\u1ed7i bu\u1ed3n v\u00e0 c\u1ea3 nh\u1eefng d\u1ecbu d\u00e0ng, th\u01b0\u01a1ng y\u00eau trong qu\u00e1 kh\u1ee9 l\u1ea1i tr\u1edf v\u1ec1.\n    T\u1eed K\u1ef3 \u0111\u00e3 t\u1eebng ch\u1ea1y tr\u1ed1n kh\u1ecfi V\u00e2n D\u1ecbch, c\u00f4 s\u1ee3 h\u00e3i s\u1ef1 \u0111\u1ed9c \u0111o\u00e1n trong t\u00ecnh y\u00eau, ham mu\u1ed1n chi\u1ebfm h\u1eefu c\u1ee7a anh. C\u00f4 y\u00eau anh \u0111\u1ed3ng th\u1eddi c\u0169ng mu\u1ed1n c\u00f3 \u0111\u01b0\u1ee3c s\u1ef1 t\u1ef1 do cho ch\u00ednh m\u00ecnh, \u0111\u01b0\u1ee3c l\u00e0m nh\u1eefng \u0111i\u1ec1u m\u00ecnh th\u00edch m\u00e0 kh\u00f4ng ph\u1ea3i d\u1ef1a theo \u00fd mu\u1ed1n c\u1ee7a ng\u01b0\u1eddi kh\u00e1c. Sau m\u01b0\u1eddi m\u1ed9t n\u0103m g\u1eb7p l\u1ea1i, V\u00e2n D\u1ecbch \u0111\u00e3 xu\u1ea5t hi\u1ec7n d\u01b0\u1edbi h\u00ecnh \u1ea3nh T\u1ed5ng gi\u00e1m \u0111\u1ed1c t\u1eadp \u0111o\u00e0n V\u00e2n Thi\u00ean \u0111\u1ea7y quy\u1ec1n l\u1ef1c v\u00e0 quy\u1ebft \u0111o\u00e1n theo \u0111u\u1ed5i c\u00f4 l\u1ea7n n\u1eefa.\n    S\u1ef1 b\u0103n kho\u0103n v\u00e0 gi\u1eb1ng x\u00e9 gi\u1eefa vi\u1ec7c quay tr\u1edf l\u1ea1i v\u1edbi V\u00e2n D\u1ecbch v\u00e0 l\u1ea1i m\u1ed9t l\u1ea7n n\u1eefa th\u1ecfa hi\u1ec7p v\u1edbi nh\u1eefng y\u00eau c\u1ea7u c\u1ee7a anh v\u1edbi b\u1ea1n g\u00e1i hay r\u1eddi xa anh v\u0129nh vi\u1ec5n \u0111\u00e3 khi\u1ebfn T\u1eed K\u1ef3 l\u1ef1a ch\u1ecdn k\u1ebft h\u00f4n h\u1ee3p \u0111\u1ed3ng c\u00f9ng Ninh Thanh, ng\u01b0\u1eddi \u0111\u00e3 theo \u0111u\u1ed5i c\u00f4 trong su\u1ed1t ba n\u0103m. Hai n\u0103m \u0111\u00e3 tr\u00f4i qua k\u1ec3 t\u1eeb \u0111\u00e1m c\u01b0\u1edbi \"gi\u1ea3\u201d v\u00e0 t\u00ecnh y\u00eau c\u00f4 d\u00e0nh cho V\u00e2n D\u1ecbch v\u1eabn c\u00f2n nh\u01b0 tr\u01b0\u1edbc. Trong khi \u0111\u00f3, s\u1ef1 ghen tu\u00f4ng c\u1ee7a Ninh Thanh d\u00e0nh cho V\u00e2n D\u1ecbch l\u1ea1i t\u00edch l\u0169y d\u1ea7n v\u00e0 thay \u0111\u1ed1i h\u1eb3n t\u00ednh c\u00e1ch \u00f4n nh\u00e3 ng\u00e0y n\u00e0o. Li\u1ec7u chuy\u1ec7n g\u00ec s\u1ebd x\u1ea3y ra v\u1edbi ba ng\u01b0\u1eddi h\u1ecd?\n    T\u00ecnh c\u1ea3m c\u1ee7a hai nh\u00e2n v\u1eadt ch\u00ednh d\u00e0nh cho nhau \u0111\u01b0\u1ee3c bi\u1ec3u hi\u1ec7n b\u1eb1ng nh\u1eefng cung b\u1eadc c\u1ea3m x\u00fac h\u00e0i h\u00f2a \u0111an xen gi\u1eefa qu\u00e1 kh\u1ee9 v\u00e0 hi\u1ec7n t\u1ea1i \u0111\u00e3 t\u1ea1o n\u00ean \u0111\u01b0\u1ee3c n\u00e9t h\u1ea5p d\u1eabn \u0111\u1eb7c bi\u1ec7t cho cu\u1ed1n ti\u1ec3u thuy\u1ebft Trung Qu\u1ed1c \"M\u00f9a tuy\u1ebft r\u01a1i\u201d.\n","category_id":"4"}