{"novel",{"article_num":"719","author":"Minh Nguy\u1ec7t Th\u00ednh Phong","category_id":"4","crawl_times":null,"created_at":null,"description":"    Chuy\u1ec7n \u0111\u01b0\u1ee3c xem nh\u01b0 ph\u1ea7n n\u1ed1i ti\u1ebfp c\u1ee7a t\u00e1c ph\u1ea9m \" Heo y\u00eau Di\u00eam V\u01b0\u01a1ng\" n\u00f3i v\u1ec1 \u0111\u1ee9a con c\u1ee7a hai ng\u01b0\u1eddi l\u00e0 Ti\u1ec3u Ma V\u01b0\u01a1ng Nghi\u00eam C\u1ea9n c\u00f9ng v\u1edbi t\u00ecnh y\u00eau \u0111\u1ea7u \u0111\u1eddi v\u00e0 c\u0169ng l\u00e0 cu\u1ed1i c\u00f9ng cu\u1ea3 c\u1eadu v\u1edbi b\u00e9 Mai Kh\u00f4i si\u00eau \u0111\u00e1ng y\u00eau.nbsp\n    \u00d4ng b\u1ed1 Nghi\u00eam L\u1ea1c c\u0169ng th\u1eadt t\u1ed1t b\u1ee5ng khi t\u1ea1o d\u1ef1ng cho hai \u0111\u1ee9a tr\u1ebb m\u1ed1i t\u00ecnh thanh mai tr\u00fac m\u00e3 tuy\u1ec7t \u0111\u1eb9p. \u0110an xen v\u1edbi \u0111\u00f3 l\u00e0 m\u1ed9t b\u00ed \u1ea9n l\u1edbn v\u1ec1 m\u1eb9 c\u1ee7a Mai Kh\u00f4i b\u1edfi b\u1ea3n th\u00e2n c\u00f4 b\u00e9 l\u00e0 m\u1ed9t t\u00e2m ng\u1eef gi\u1ea3 lu\u00f4n ph\u1ea3i \u0111\u1ed1i di\u1ec7n v\u1edbi nh\u1eefng th\u1ee9 \u0111\u00e1ng s\u1ee3 xung quang m\u00ecnh. B\u1edfi v\u1eady \u00f4ng b\u00e0 ta m\u1edbi c\u00f3 c\u00e2u :\" T\u00e0i t\u00ecnh chi l\u1eafm cho tr\u1eddi \u0111\u1ea5t ghen\" c\u0169ng th\u1eadt t\u1ed9i nghi\u1ec7p cho b\u00e9 Mai Kh\u00f4i khi ba m\u1eb9 ly th\u00e2n ph\u1ea3i s\u1ed1ng c\u00f9ng v\u1edbi m\u1ee5 d\u00ec gh\u1ebb th\u1ebf nh\u01b0ng xung quanh em lu\u00f4n c\u00f3 nh\u1eefng ng\u01b0\u1eddi b\u1ea1n th\u00e2n lu\u00f4n y\u00eau qu\u00fd em c\u00f2n c\u00f3 c\u1ea3 Nghi\u00eam C\u1ea7n ban \u0111\u1ea7u th\u00ec ch\u1ecdc em d\u1eef l\u1eafm \u0111\u1ebfn l\u00fac sau m\u1edbi nh\u1eadn ra \u0111\u01b0\u1ee3c t\u00ecnh y\u00eau c\u1ee7a m\u00ecnh.nbsp\n    Tr\u00edch \u0111o\u1ea1n:\n    Nghi\u00eam C\u1ea9n b\u1ecb Mai Kh\u00f4i k\u00e9o tay v\u00f4 c\u00f9ng m\u1ea5t t\u1ef1 nhi\u00ean, nh\u01b0ng tr\u01b0\u1edbc m\u1eb7t Nghi\u00eam L\u1ea1c v\u00e0 Ti\u1ec3u Ti\u1ec3u, c\u1eadu c\u0169ng kh\u00f4ng d\u00e1m gi\u1eb1ng co. Mai Kh\u00f4i nh\u00ecn c\u1eadu, l\u1ea1i n\u00f3i v\u1edbi Ti\u1ec3u Ti\u1ec3u: \u201cV\u1eady anh c\u0169ng ng\u1ee7 th\u00f4i\u201d.\n    \u201c\u0110\u00fang, hai \u0111\u1ee9a \u0111\u1ec1u c\u1ea7n ng\u1ee7 s\u1edbm m\u1ed9t ch\u00fat, ng\u00e0y mai ph\u1ea3i c\u00f9ng \u0111i h\u1ecdc.\u201d\n    Mai Kh\u00f4i n\u1edf n\u1ee5 c\u01b0\u1eddi, ngoan ngo\u00e3n \u0111\u1ec3 Ti\u1ec3u Ti\u1ec3u d\u1eaft tay quay v\u1ec1 ph\u00f2ng \u0111i ng\u1ee7. Nghi\u00eam C\u1ea9n b\u1ecb Nghi\u00eam L\u1ea1c nh\u00ecn ch\u1eb1m ch\u1eb1m, c\u00fai \u0111\u1ea7u xu\u1ed1ng, m\u0169i ch\u00e2n c\u1ecd tr\u00ean s\u00e0n nh\u00e0, kh\u00f4ng d\u00e1m ph\u1ea3n kh\u00e1ng. Nghi\u00eam L\u1ea1c nh\u00ecn c\u1eadu h\u1ed3i l\u00e2u, cu\u1ed1i c\u00f9ng l\u00ean ti\u1ebfng: \u201cBi\u1ebft sai ch\u01b0a?\u201d.\n    \u201c\u1eeam\u201d, Nghi\u00eam C\u1ea9n h\u1eadm h\u1ef1c.\n    \u201cN\u00f3i chuy\u1ec7n.\u201d\n    \u201cB\u1ed1, con bi\u1ebft sai r\u1ed3i\u201d, Nghi\u00eam C\u1ea9n n\u00f3i nh\u1ecf, c\u1ea3m th\u1ea5y r\u1ea5t \u1ea5m \u1ee9c.\n    \u201cSai \u1edf \u0111\u00e2u?\u201d\n    \u201c\u1eeam, ch\u00ednh l\u00e0, kh\u00f4ng n\u00ean l\u00e0m b\u1ecb th\u01b0\u01a1ng ng\u01b0\u1eddi kh\u00e1c.\u201d\n    Nghi\u00eam L\u1ea1c kh\u00f4ng n\u00f3i g\u00ec, trong l\u00f2ng Nghi\u00eam C\u1ea9n r\u1ea5t c\u0103ng th\u1eb3ng, qua m\u1ed9t l\u00e1t cu\u1ed1i c\u00f9ng nghe th\u1ea5y b\u1ed1 n\u00f3i: \u201c\u0110i ng\u1ee7 \u0111i, ng\u00e0y mai \u0111i h\u1ecdc\u201d. L\u00fac n\u00e0y Nghi\u00eam C\u1ea9n m\u1edbi th\u1edf ph\u00e0o m\u1ed9t c\u00e1i, ch\u00e1n ch\u01b0\u1eddng \u0111i v\u00e0o trong ph\u00f2ng.\n","id":"719","is_category_hot":false,"is_category_recommend":false,"is_category_this_week_hot":false,"is_classic":null,"is_classic_action":null,"is_serializing":false,"is_show":true,"last_update":"04-11-2016","link":"http:\/\/cuongtruyen.com\/truyen\/bai-hoc-yeu-duong-cua-tieu-ma-vuong\/719.html","name":"B\u00e0i H\u1ecdc Y\u00eau \u0110\u01b0\u01a1ng C\u1ee7a Ti\u1ec3u Ma V\u01b0\u01a1ng","num":"78","pic":"http:\/\/cuongtruyen.com\/images\/info\/bai-hoc-yeu-duong-cua-tieu-ma-vuong\/719.jpg","updated_at":"2016-11-04T12:46:26+08:00"}}