{"id":"2417","article_num":"2417","author":"\u00c1m Ma S\u01b0","is_serializing":false,"last_update":"12-11-2016","name":"D\u01b0\u1ee3c Th\u1ea7n","pic":null,"description":"    H\u1eafn \u0111\u01b0\u1ee3c ng\u01b0\u1eddi \u0111\u1eddi c\u00f4ng nh\u1eadn l\u00e0 c\u01b0\u1eddng gi\u1ea3 m\u1ea1nh nh\u1ea5t \u0111\u1ea1i l\u1ee5c. L\u00e0 Linh D\u01b0\u1ee3c Th\u00e1nh S\u01b0 duy nh\u1ea5t c\u1ee7a \u0111\u1ea1i l\u1ee5c T\u01b0 \u0110\u1eb7c \u00c2n.\n    Ki\u1ec7t S\u00e2m! M\u1ed9t thi\u00ean t\u00e0i xu\u1ea5t s\u1eafc c\u1ee7a \u0111\u1ea1i l\u1ee5c T\u01b0 \u0110\u1eb7c \u00c2n \u0111\u00e3 g\u1eb7p ph\u1ea3i m\u1ed9t vi\u1ec7c ngo\u00e0i \u00fd mu\u1ed1n trong m\u1ed9t l\u1ea7n ra luy\u1ec7n d\u01b0\u1ee3c. H\u1eafn ti\u1ebfn v\u00e0o th\u1eddi kh\u00f4ng lo\u1ea1n l\u01b0u, tr\u1edf v\u1ec1 th\u1eddi \u0111\u1ea1i Linh D\u01b0\u1ee3c man hoang ba ng\u00e0n n\u0103m tr\u01b0\u1edbc.\n    Th\u1eddi \u0111\u1ea1i l\u00fac b\u1ea5y gi\u1edd, Linh D\u01b0\u1ee3c S\u01b0 c\u00f2n ch\u01b0a c\u00f3 ph\u00e1t tri\u1ec3n m\u1ea1nh m\u1ebd, so v\u1edbi Linh D\u01b0\u1ee3c S\u01b0 \u1edf th\u1eddi \u0111\u1ea1i m\u00e0 Ki\u1ec7t S\u00e2m \u0111ang s\u1ed1ng th\u00ec thua k\u00e9m nhi\u1ec1u l\u1eafm. Sau khi tr\u1ecdng sinh tr\u1edf v\u1ec1 th\u1eddi k\u1ef3 c\u1ed5 \u0111\u1ea1i, Ki\u1ec7t S\u00e2m l\u1ee3i d\u1ee5ng l\u1ef1c l\u01b0\u1ee3ng c\u1ee7a b\u1ea3n th\u00e2n, h\u1eafn v\u01b0\u01a1n l\u00ean tr\u1edf th\u00e0nh c\u01b0\u1eddng gi\u1ea3 m\u1ea1nh nh\u1ea5t c\u1ee7a \u0111\u1ea1i l\u1ee5c, \u0111\u1ed9t ph\u00e1 g\u00f4ng c\u00f9m xi\u1ec1ng x\u00edch ki\u1ebfp tr\u01b0\u1edbc c\u1ee7a m\u00ecnh!\n    Nh\u00f3m d\u1ecbch DungNhi\n    Ngu\u1ed3n: vipvandan\n","category_id":"1"}