{"id":"295","article_num":"295","author":"L\u01b0u Tam Tam","is_serializing":false,"last_update":"04-11-2016","name":"Ng\u1ea1i G\u00ec L\u00ean Gi\u01b0\u1eddng","pic":null,"description":"    <i>Ng\u1ea1i G\u00ec L\u00ean Gi\u01b0\u1eddng<\/i> k\u1ec3 v\u1ec1 chuy\u1ec7n t\u00ecnh y\u00eau gi\u1eefa 2 con ng\u01b0\u1eddi v\u1edbi 2 t\u00ednh c\u00e1ch k\u00ec l\u1ea1. M\u1ed9t ng\u01b0\u1eddi \u0111\u00e0n \u00f4ng c\u1ee9ng nh\u1eafc l\u1ea1nh l\u00f9ng - T\u1ed1ng L\u0103ng Th\u1ea7n. M\u1ed9t ng\u01b0\u1eddi ph\u1ee5 n\u1eef t\u00ednh c\u00e1ch tinh qu\u00e1i - H\u1ee9a T\u1eed Ng\u01b0. Hai ng\u01b0\u1eddi v\u1ed1n l\u00e0 b\u1ea1n h\u1ecdc c\u1ee7a nhau, nh\u01b0ng kh\u00f4ng hi\u1ec3u sao tr\u1eddi xui \u0111\u1ea5t khi\u1ebfn l\u00ean gi\u01b0\u1eddng v\u1edbi nhau.\n    Anh lu\u00f4n lu\u00f4n kh\u00f4ng thay \u0111\u1ed5i, c\u00f3 m\u1ed9t s\u1ef1 quan t\u00e2m r\u1ea5t l\u1edbn d\u00e0nh cho c\u00f4 nh\u01b0ng ch\u1ec9 th\u1ec3 hi\u1ec7n qua nh\u1eefng c\u00e2u r\u1ea7y la. C\u00f4 trong l\u00f2ng r\u00f5 r\u00e0ng lu\u00f4n c\u00f3 anh nh\u01b0ng l\u1ea1i th\u1ec3 hi\u1ec7n nh\u01b0 ch\u01b0a bao gi\u1edd \u0111\u1ec3 t\u00e2m\n    \" T\u00f4i \u0111i qua r\u1ea5t nhi\u1ec1u c\u00e2y c\u1ea7u \u0111\u1eb9p, th\u1ea5y qua r\u1ea5t nhi\u1ec1u \u0111\u00e1m m\u00e2y, u\u1ed1ng qua r\u1ea5t nhi\u1ec1u lo\u1ea1i r\u01b0\u1ee3u, nh\u01b0ng l\u1ea1i duy nh\u1ea5t ch\u1ec9 y\u00eau m\u1ed9t ng\u01b0\u1eddi c\u00f9ng tu\u1ed5i v\u1edbi t\u00f4i.\"\n    Ti\u1ebfp theo s\u1ebd x\u1ea3y ra chuy\u1ec7n g\u00ec? Hai ng\u01b0\u1eddi b\u1ecdn h\u1ecd s\u1ebd vi\u1ebft ti\u1ebfp c\u00e2u chuy\u1ec7n t\u00ecnh y\u00eau n\u00e0y ra sao ?\n","category_id":"4"}