{"id":"2002","article_num":"2002","author":"Linh L\u00f2e Lo\u1eb9t","is_serializing":false,"last_update":"06-11-2016","name":"Ai M\u1edbi L\u00e0 Con Trai","pic":null,"description":"    Ai M\u1edbi L\u00e0 Con Trai m\u1ed9t truy\u1ec7n teen \u0111\u1ea7y h\u00e0i h\u01b0\u1edbc m\u00e0  mu\u1ed1n gi\u1edbi thi\u1ec7u \u0111\u1ebfn b\u1ea1n \u0111\u1ecdc.\n    Lam Minh Nh\u1eadt: Con c\u1ee7a t\u1eadp \u0111o\u00e0n AL n\u1ed5i ti\u1ebfng v\u1ec1 \u0111\u00e1 qu\u00fd,m\u1ed9t t\u1eadp \u0111o\u00e0n h\u00f9ng m\u1ea1nh nh\u1ea5t. T\u00ean c\u1ee7a n\u00f3 l\u00e0 t\u00ean con trai,kh\u00f4ng nh\u1eefng th\u1ebf t\u00ednh c\u00e1ch con trai c\u1ee7a n\u00f3 \u0111\u00e3 \u0111\u01b0\u1ee3c coi nh\u01b0 \"thu\u1ea7n nhuy\u1ec5n\" trong t\u00e2m h\u1ed3n c\u0169ng nh\u01b0 s\u00e2u l\u1eafng trong tim n\u00f3. - N\u00f3.\n    Nguy\u1ec5n Minh Phong: Con c\u1ee7a t\u1eadp \u0111o\u00e0n \u0111\u00e1 qu\u00fd l\u1edbn th\u1ee9 nh\u1ea5t \u1edf th\u00e0nh ph\u1ed1 A,t\u1eadp \u0111o\u00e0n kh\u00f4ng k\u00e9m g\u00ec t\u1eadp \u0111o\u00e0n nh\u00e0 n\u00f3. Nh\u1ecf mang t\u00ednh c\u00e1ch con trai ph\u1ea3i g\u1ecdi l\u00e0 \"\u0111\u1eb7c s\u1ec7t\" c\u00f9ng v\u1edbi t\u00ean Phong \u0111\u1ea7y nam t\u00ednh. - Nh\u1ecf\n    Ho\u00e0ng Minh Th\u1ee5y: Con c\u1ee7a nh\u00e0 thi\u1ebft k\u1ebf n\u1ed5i ti\u1ebfng nh\u1ea5t v\u00f9ng ch\u00e2u \u00c1 v\u1ec1 trang s\u1ee9c c\u0169ng nh\u01b0 th\u1eddi trang. N\u00e0ng kh\u00f4ng nh\u1eefng s\u1edf h\u1eefu t\u00ean con trai m\u00e0 c\u1ea3 ng\u01b0\u1eddi n\u00e0ng t\u1eeb gi\u1ecdng n\u00f3i hay h\u00e0nh \u0111\u1ed9ng c\u0169ng m\u1ea1nh m\u1ebd nh\u01b0 con trai. -N\u00e0ng\n    Cao Ho\u00e0ng Nam: Con c\u1ee7a t\u1eadp \u0111o\u00e0n AZ l\u1edbn kh\u1eafp v\u00f9ng ch\u00e2u \u00c2u. Anh \u0111\u01b0\u1ee3c \u0111\u01b0a sang n\u01b0\u1edbc Vi\u1ec7t h\u1ecdc \u0111\u1ec3 bi\u1ebft qu\u00ea h\u01b0\u01a1ng c\u1ee7a m\u00ecnh,\u0111\u1ed3ng th\u1eddi gi\u1ea3m \u0111i t\u00ednh ngang b\u01b0\u1edbng c\u1ee7a m\u00ecnh. -Anh\n","category_id":"4"}