{"novel",{"article_num":"1900","author":"vohinhnhubongtoi","category_id":"4","crawl_times":null,"created_at":null,"description":"    S\u01b0u t\u1ea7m\n    Tr\u00edch \u0111o\u1ea1n:\n    Th\u1ea5y h\u1eafn kh\u1ecfe m\u1ea1nh , t\u01b0\u01a1i t\u1ec9nh n\u00f3 c\u0169ng m\u1eebng l\u1eafm ch\u1ee9 ? Kh\u00f4ng hi\u1ec3u sao l\u1ea1i th\u1ed1t ra c\u00e2u \u0111\u00f3 ?\n    - \u01a0 kh\u00f4ng ph\u1ea3i !!! \u00dd t\u00f4i l\u00e0 \u2026 sao c\u1eadu l\u1ea1i \u1edf \u0111\u00e2y ?? N\u00f3 l\u00fang t\u00fang.\n    - \u0110\u1eebng c\u00f3 chuy\u1ec3n \u0111\u1ec1 t\u00e0i nhanh th\u1ebf ch\u1ee9 ? T\u00f4i ch\u01b0a ngo\u1ebbo l\u00e0 nh\u1edd \u00f4ng tr\u1eddi ph\u00f9 h\u1ed9 ! Ai b\u1ea3o t\u00f4i t\u1ed1t b\u1ee5ng qu\u00e1 n\u00ean m\u1edbi x\u00f4ng ra \u0111\u1ee1 chai bia h\u1ed9 ng\u01b0\u1eddi ta ! V\u1eady m\u00e0 \u0111\u01b0\u1ee3c \u0111\u1ed1i x\u1eed th\u1ebf \u0111\u1ea5y ??? C\u00f2n t\u00f4i \u1edf \u0111\u00e2y l\u00e0 v\u00ec : T\u00f4i \u0111\u00e3 tr\u1edf th\u00e0nh nh\u00e2n vi\u00ean c\u1ee7a qu\u00e1n n\u00e0y . K\u1ec3 \u2013 t\u1eeb \u2013 h\u00f4m \u2013 nay !!! H\u1eafn t\u1ec9nh b\u01a1 tu\u00f4n m\u1ed9t tr\u00e0ng .\n    N\u00f3 h\u00e1 h\u1ed1c m\u1ed3m toan th\u1eafc m\u1eafc th\u00ec ti\u1ebfng b\u00e0 ch\u1ee7 Go Home vang l\u00ean ch\u1eafc n\u1ecbch :\n    - Ph\u1ea3i \u0111\u00f3 ! C\u1eadu \u1ea5y l\u00e0 nh\u00e2n vi\u00ean t\u00f4i m\u1edbi tuy\u1ec3n xong !\n    - Nh\u01b0ng c\u00f4 tuy\u1ec3n c\u1eadu ta l\u00e0m vi\u1ec7c g\u00ec ?\n    - Th\u00ec ph\u1ee5c v\u1ee5 , b\u01b0ng b\u00ea , b\u1ed3i b\u00e0n \u2026 \u0111\u1ee7 ki\u1ec3u ! T\u00f3m l\u1ea1i l\u00e0 ch\u00e2n sai v\u1eb7t !\n    - C\u00f2n ch\u00e1u th\u00ec sao ??? Ch\u1eb3ng ph\u1ea3i ch\u00e1u v\u1eabn l\u00e0m c\u00f4ng vi\u1ec7c ph\u1ee5 v\u1ee5 c\u01a1 m\u00e0 ? N\u00f3 ph\u1ea3n \u0111\u1ed1i tr\u01b0\u1edbc nguy c\u01a1 b\u1ecb gi\u1eadt m\u1ea5t ch\u1ed7 l\u00e0m .\n    - Ch\u00e1u c\u1ee9 l\u00e0m c\u00f4ng vi\u1ec7c c\u1ee7a m\u00ecnh ! C\u00f3 g\u00ec \u0110\u00ecnh D\u01b0\u01a1ng s\u1ebd gi\u00fap \u0111\u1ee1 th\u00eam !! D\u00f9 sao qu\u00e1n d\u1ea1o n\u00e0y c\u0169ng \u0111\u00f4ng kh\u00e1ch . C\u00f3 hai ng\u01b0\u1eddi ch\u00e1u s\u1ebd \u0111\u1ee1 v\u1ea5t v\u1ea3 h\u01a1n ! Ph\u1ea3i kh\u00f4ng ??? B\u00e0 ch\u1ee7 nh\u00ecn n\u00f3 c\u01b0\u1eddi .\n","id":"1900","is_category_hot":false,"is_category_recommend":false,"is_category_this_week_hot":false,"is_classic":null,"is_classic_action":null,"is_serializing":false,"is_show":true,"last_update":"06-11-2016","link":"http:\/\/cuongtruyen.com\/truyen\/doi-trat-tu-va-nh\u00adung-ke-thich-dua\/1900.html","name":"\u0110\u1ed9i Tr\u1eadt T\u1ef1 V\u00e0 Nh\u00ad\u1eefng K\u1ebb Th\u00edch \u0110\u00f9a","num":"20","pic":"http:\/\/cuongtruyen.com\/images\/info\/doi-trat-tu-va-nh\u00adung-ke-thich-dua\/1900.jpg","updated_at":"2016-11-06T21:27:54+08:00"}}