{"novel",{"article_num":"303","author":"T\u00e0o \u0110\u00ecnh","category_id":"4","crawl_times":null,"created_at":null,"description":"    \"Y\u00eau anh h\u01a1n c\u1ea3 t\u1eed th\u1ea7n\" l\u00e0 m\u1ed9t b\u1ea3n t\u00ecnh ca \u0111\u00fang ngh\u0129a v\u1edbi t\u1ea5t c\u1ea3 nh\u1eefng cung b\u1eadc c\u1ea3m x\u00fac, c\u00f3 ng\u1ecdt ng\u00e0o, c\u00f3 cay \u0111\u1eafng t\u1ef1a nh\u01b0 h\u01b0\u01a1ng v\u1ecb c\u1ee7a m\u1ed9t thanh chocolate. \u0110\u1ebfn v\u1edbi c\u00e2u chuy\u1ec7n n\u00e0y, ng\u01b0\u1eddi \u0111\u1ecdc c\u00f3 th\u1ec3 c\u1ea3m nh\u1eadn \u0111\u01b0\u1ee3c s\u1ee9c m\u1ea1nh c\u1ee7a t\u00ecnh y\u00eau ch\u00e2n ch\u00ednh, m\u1ea1nh h\u01a1n m\u1ecdi r\u00e0o c\u1ea3n \u0111\u1ecbnh ki\u1ebfn x\u00e3 h\u1ed9i, m\u1ea1nh h\u01a1n c\u1ea3 s\u1ed1 m\u1ec7nh hay c\u00e1i ch\u1ebft. N\u1ebfu b\u1ea1n \u0111\u00e3 t\u1eebng \u0111\u1ecdc Ki\u1ebfp Tr\u01b0\u1edbc Em \u0110\u00e3 Ch\u00f4n C\u1ea5t Cho Anh th\u00ec ch\u1eafc h\u1eb3n s\u1ebd bi\u1ebft truy\u1ec7n c\u1ee7a T\u00e0o \u0110\u00ecnh cu\u1ed1n h\u00fat th\u1ebf n\u00e0o.\n    Cu\u1ed9c \u0111\u1eddi con ng\u01b0\u1eddi l\u1eafm n\u1ed7i \u00e9o le, \u0111\u1eafng cay nh\u01b0ng c\u0169ng kh\u00f4ng \u00edt ni\u1ec1m vui, h\u1ea1nh ph\u00fac, nh\u1ea5t l\u00e0 nh\u1eefng l\u00fac \u0111\u01b0\u1ee3c ng\u01b0\u1eddi kh\u00e1c y\u00eau th\u01b0\u01a1ng, quan t\u00e2m, ch\u0103m s\u00f3c, nh\u1ea5t n\u1eefa l\u00e0 s\u1ef1 y\u00eau th\u01b0\u01a1ng \u1ea5y d\u00e0nh cho ta khi ta s\u1eafp b\u1ecb T\u1eed th\u1ea7n mang \u0111i. Cu\u1ed9c s\u1ed1ng c\u0169ng \u0111\u00e2u ch\u1ec9 gi\u1ea3n \u0111\u01a1n l\u00e0 khi vui th\u00ec c\u01b0\u1eddi, c\u00f2n khi bu\u1ed3n th\u00ec kh\u00f3c. Ch\u1ec9 tr\u1ebb con m\u1edbi c\u00f3 th\u1ec3 l\u00e0m \u0111\u01b0\u1ee3c nh\u01b0 v\u1eady th\u00f4i! Ng\u01b0\u1eddi l\u1edbn ph\u1ee9c t\u1ea1p h\u01a1n nhi\u1ec1u, \u0111\u00e2u c\u00f3 th\u1ec3 h\u1ed3n nhi\u00ean, ch\u00e2n th\u00e0nh v\u1edbi ch\u00ednh m\u00ecnh nh\u01b0 th\u1ebf v\u00e0 \u0111\u00f4i khi c\u0169ng kh\u00f4ng th\u1ec3 l\u00e0m theo nh\u1eefng g\u00ec m\u00ecnh mu\u1ed1n, m\u00ecnh th\u00edch \u0111\u01b0\u1ee3c. \u0110\u00f4i l\u00fac, vui c\u0169ng kh\u00f4ng th\u1ec3 c\u01b0\u1eddi v\u00e0 bu\u1ed3n l\u1ea1i kh\u00f4ng th\u1ec3 kh\u00f3c.\n    M\u1ec5 B\u1ed1i v\u1ed1n l\u00e0 m\u1ed9t ti\u00ean n\u1eef tr\u00ean tr\u1eddi nh\u01b0ng khi \u0111\u1ea7u thai xu\u1ed1ng tr\u1ea7n v\u1edbi m\u1ed9t mong mu\u1ed1n \u0111\u01b0\u1ee3c th\u1eed c\u1ea3m gi\u00e1c c\u1ee7a con ng\u01b0\u1eddi. V\u00e0 c\u00f4 \u0111\u00e3 l\u00e0m m\u1ed9t \"con ng\u01b0\u1eddi\" th\u1ef1c s\u1ef1. C\u00f4 l\u00e0 hi\u1ec7n th\u00e2n \u0111\u1ea7y \u0111\u1ee7 nh\u1ea5t v\u00e0 ch\u00e2n th\u1ef1c nh\u1ea5t c\u1ee7a con ng\u01b0\u1eddi. Gi\u1eefa kh\u00f3c v\u00e0 c\u01b0\u1eddi, con ng\u01b0\u1eddi l\u00e0m g\u00ec nhi\u1ec1u h\u01a1n v\u00e0 l\u00e0m g\u00ec d\u1ec5 h\u01a1n? C\u01b0\u1eddi... \u0110\u1ea7u thai xu\u1ed1ng c\u00f5i tr\u1ea7n, ban \u0111\u1ea7u M\u1ec5 B\u1ed1i ch\u01b0a bi\u1ebft c\u01b0\u1eddi v\u00e0 c\u0169ng ch\u1eb3ng bi\u1ebft kh\u00f3c nh\u01b0ng c\u00f4 \u0111\u00e3 t\u1eadp v\u00e0 bi\u1ebft c\u01b0\u1eddi tr\u01b0\u1edbc. C\u00f2n nh\u1eefng gi\u1ecdt n\u01b0\u1edbc m\u1eaft, ph\u1ea3i cu\u1ed1i \u0111\u1eddi c\u00f4 m\u1edbi c\u00f3 \u0111\u01b0\u1ee3c n\u00f3. D\u00f9 c\u00f4 khao kh\u00e1t \u0111\u01b0\u1ee3c n\u1ebfm \"th\u1ee9 n\u01b0\u1edbc ch\u1ea3y ra t\u1eeb m\u1eaft\" \u1ea5y t\u1eeb l\u00e2u l\u1eafm r\u1ed3i. Nh\u1eefng l\u00fac bu\u1ed3n, mu\u1ed1n kh\u00f3c m\u00e0 m\u1eaft c\u1ee9 kh\u00f4 r\u00e1o ho\u1ea3nh. C\u00f4 xu\u1ed1ng tr\u1ea7n \u0111\u1ec3 l\u00e0m g\u00ec? \u0110\u1ec3 \u0111\u01b0\u1ee3c bi\u1ebft v\u1ecb c\u1ee7a n\u01b0\u1edbc m\u1eaft! \u0110\u1eebng b\u1ea3o n\u1ee5 c\u01b0\u1eddi l\u00e0 hi\u1ec7n th\u00e2n c\u1ee7a ni\u1ec1m vui, h\u1ea1nh ph\u00fac nh\u00e9! V\u00e0 c\u0169ng \u0111\u1eebng b\u1ea3o n\u01b0\u1edbc m\u1eaft l\u00e0 k\u1ebft \u0111\u1ecdng c\u1ee7a n\u1ed7i bu\u1ed3n. Khi vui, ng\u01b0\u1eddi ta c\u01b0\u1eddi \u0111\u00e3 \u0111\u00e0nh nh\u01b0ng l\u00fac bu\u1ed3n, ng\u01b0\u1eddi ta v\u1eabn c\u00f3 th\u1ec3 c\u01b0\u1eddi \u0111\u01b0\u1ee3c, th\u1eadm ch\u00ed l\u00e0 c\u01b0\u1eddi r\u1ea5t l\u1edbn - c\u00e1i \u0111i\u1ec7u c\u01b0\u1eddi chua ch\u00e1t, cay c\u1ef1c. Song ng\u01b0\u1eddi ta c\u00f3 d\u1ec5 kh\u00f3c \u0111\u01b0\u1ee3c kh\u00f4ng? N\u1ed7i bu\u1ed3n s\u00e2u s\u1eafc l\u00e0 n\u1ed7i bu\u1ed3n l\u1eb7n v\u00e0o trong. Nh\u1eefng gi\u1ecdt n\u01b0\u1edbc m\u1eaft th\u1ef1c s\u1ef1 ch\u1ec9 ch\u1ea3y ra khi ng\u01b0\u1eddi ta m\u00e3n nguy\u1ec7n, ng\u01b0\u1eddi ta h\u1ea1nh ph\u00fac... Con ng\u01b0\u1eddi s\u1ed1ng trong \u0111\u1eddi \u0111\u1ec3 ki\u1ebfm t\u00ecm nh\u1eefng gi\u1ecdt n\u01b0\u1edbc m\u1eaft nh\u01b0 th\u1ebf v\u00e0 c\u0169ng l\u00e0 ki\u1ebfm t\u00ecm nh\u1eefng ni\u1ec1m vui s\u1ed1ng, ni\u1ec1m h\u1ea1nh ph\u00fac tr\u00ean c\u00f5i \u0111\u1eddi... \u0110\u00f3 l\u00e0 tri\u1ebft l\u00ed m\u00e0 T\u00e0o \u0110\u00ecnh mu\u1ed1n g\u1eedi t\u1edbi ng\u01b0\u1eddi \u0111\u1ecdc.\n    M\u1ea1c Ng\u00f4n Hy, ch\u00e0ng trai tho\u1ea1t \u0111\u1ea7u khi\u1ebfn ng\u01b0\u1eddi \u0111\u1ecdc th\u1ea5y \u0111\u00e1ng gh\u00e9t v\u00ec th\u00f3i huy\u00eanh hoang, ng\u1ed7 ng\u01b0\u1ee3c, l\u1ea1nh l\u00f9ng \u0111\u1ebfn t\u00e0n nh\u1eabn. Nh\u01b0ng sau l\u1ea1i khi\u1ebfn ng\u01b0\u1eddi \u0111\u1ecdc c\u1ea3m \u0111\u1ed9ng v\u00ec n\u1ed7i b\u1ea5t h\u1ea1nh m\u00e0 anh ph\u1ea3i ch\u1ecbu \u0111\u1ef1ng v\u00e0 h\u01a1n h\u1ebft l\u00e0 v\u00ec nh\u00e2n t\u00ednh \u1ea9n s\u00e2u trong t\u00e2m h\u1ed3n anh. M\u1ea1c Ng\u00f4n Hy c\u0169ng l\u00e0 hi\u1ec7n th\u00e2n \u0111\u1ea7y \u0111\u1ee7 nh\u1ea5t c\u1ee7a \"con ng\u01b0\u1eddi\". Anh mang trong m\u00ecnh n\u1ed7i \u0111au c\u1ee7a c\u0103n b\u1ec7nh th\u1ebf k\u1ec9 HIV\/AIDS. Nh\u01b0ng kh\u00f4ng ph\u1ea3i v\u00ec anh ch\u01a1i b\u1eddi, \u0111\u1ed3i tr\u1ee5y m\u00e0 v\u00ec anh th\u01b0\u01a1ng ng\u01b0\u1eddi v\u00e0 c\u1ea3 tin qu\u00e1! S\u1ef1 tr\u1ea3 gi\u00e1 \u1ea5y c\u00f3 qu\u00e1 \u0111\u1eaft v\u00e0 b\u1ea5t c\u00f4ng? Anh l\u00e0 m\u1ed9t con ng\u01b0\u1eddi v\u00ec anh c\u0169ng y\u1ebfu \u0111u\u1ed1i, c\u0169ng s\u1ee3 c\u00f4 \u0111\u01a1n, s\u1ee3 b\u1ecb \u0111\u1ed3ng lo\u1ea1i xa l\u00e1nh, c\u0169ng khao kh\u00e1t \u0111\u01b0\u1ee3c y\u00eau th\u01b0\u01a1ng... Khi ng\u01b0\u1eddi ta c\u00e0ng y\u1ebfu \u0111u\u1ed1i, ng\u01b0\u1eddi ta c\u00e0ng t\u1ecf ra m\u00ecnh m\u1ea1nh m\u1ebd v\u00e0 ra s\u1ee9c \u1ee9c hi\u1ebfp ng\u01b0\u1eddi kh\u00e1c. Khi ng\u01b0\u1eddi ta s\u1ee3 c\u00f4 \u0111\u01a1n, ng\u01b0\u1eddi ta c\u00e0ng t\u1ecf ra l\u1ea1nh l\u00f9ng, t\u00e1ch bi\u1ec7t v\u1edbi \u0111\u1ed3ng lo\u1ea1i... Con ng\u01b0\u1eddi l\u00e0 th\u1ebf!\n    C\u00e2u chuy\u1ec7n t\u00ecnh y\u00eau l\u00e3ng m\u1ea1n, \u00e9o le, h\u00e0m ch\u1ee9a bao b\u00e0i h\u1ecdc v\u1ec1 nh\u00e2n sinh, v\u1ec1 con ng\u01b0\u1eddi. \u0110\u1ecdc truy\u1ec7n, con ng\u01b0\u1eddi d\u01b0\u1eddng nh\u01b0 th\u1ea5u hi\u1ec3u m\u00ecnh h\u01a1n, ti\u1ebfn g\u1ea7n \u0111\u1ebfn m\u00ecnh h\u01a1n tr\u00ean h\u00e0nh tr\u00ecnh ki\u1ebfm t\u00ecm v\u00e0 kh\u00e1m ph\u00e1 ch\u00ednh b\u1ea3n th\u00e2n m\u00ecnh. V\u00e0 \u0111\u1ecdc n\u00f3, \u0111\u1ed9c gi\u1ea3 c\u0169ng d\u1ec5 b\u1ecb lay \u0111\u1ed9ng. N\u1ebfu \u0111\u1eb7t v\u00e0o \u0111\u1ecba v\u1ecb M\u1ec5 B\u1ed1i l\u00fac \u1ea5y, ch\u1eafc h\u1eb3n ng\u01b0\u1eddi \u0111\u1ecdc c\u0169ng s\u1ebd nguy\u1ec7n hy sinh \u0111\u1ec3 c\u1ee9u s\u1ed1ng ng\u01b0\u1eddi m\u00ecnh y\u00eau. C\u00f2n khi \u0111\u00e3 g\u1ea5p s\u00e1ch l\u1ea1i, b\u01b0\u1edbc ra \u0111\u01b0\u1eddng v\u00e0 h\u00f2a v\u00e0o d\u00f2ng ng\u01b0\u1eddi h\u1ed1 h\u1ea3, ch\u00fang ta c\u0169ng kh\u00f4ng bi\u1ebft c\u00f2n gi\u1eef \u0111\u01b0\u1ee3c nh\u1eefng \u00fd ngh\u0129a trong tr\u1ebbo, cao th\u01b0\u1ee3ng \u1ea5y kh\u00f4ng, nh\u01b0ng ph\u1ea3i ch\u1eafc ch\u1eafn m\u1ed9t \u0111i\u1ec1u r\u1eb1ng \"Y\u00eau anh h\u01a1n c\u1ea3 T\u1eed th\u1ea7n\" v\u1eabn c\u00f2n vang v\u1ecdng m\u00e3i.\n","id":"303","is_category_hot":false,"is_category_recommend":false,"is_category_this_week_hot":false,"is_classic":null,"is_classic_action":null,"is_serializing":false,"is_show":true,"last_update":"04-11-2016","link":"http:\/\/cuongtruyen.com\/truyen\/yeu-anh-hon-ca-tu-than\/303.html","name":"Y\u00eau Anh H\u01a1n C\u1ea3 T\u1eed Th\u1ea7n","num":"17","pic":"http:\/\/cuongtruyen.com\/images\/info\/yeu-anh-hon-ca-tu-than\/303.jpg","updated_at":"2016-11-04T00:30:32+08:00"}}