{"novel",{"article_num":"240","author":"Nh\u1ea1c Nhan","category_id":"4","crawl_times":null,"created_at":null,"description":"    Gi\u1edbi thi\u1ec7u:\n    Truy\u1ec7n Cu\u1ed3ng Th\u00fa c\u1ee7a t\u00e1c gi\u1ea3 Nh\u1ea1c Nhan l\u00e0 m\u1ed9t c\u00e2u chuy\u1ec7n t\u00ecnh y\u00eau ng\u1ecdt ng\u00e0o. C\u00f4 s\u1eb5n s\u00e0ng gi\u00fap \u0111\u1ee1 hy sinh kh\u00f4ng m\u00e0ng h\u1ea1nh ph\u00fac, danh d\u1ef1 b\u1ea3n th\u00e2n ch\u1ec9 v\u00ec h\u1ea1nh ph\u00fac gia \u0111\u00ecnh.\n    Anh v\u00ec y\u00eau c\u00f4 v\u00e0 ch\u1ea5p nh\u1eadn b\u1ecf ra t\u1ea5t c\u1ea3, chung th\u1ee7y m\u1ed9t t\u00ecnh y\u00eau v\u1edbi c\u00f4. B\u1ec1 ngo\u00e0i c\u00f4 th\u1eadt c\u1edfi m\u1edf nh\u01b0ng b\u00ean trong n\u1ed9i t\u00e2m thu\u1ea7n ch\u1ea5t l\u00e0 m\u1ed9t ng\u01b0\u1eddi ph\u1ee5 n\u1eef truy\u1ec1n th\u1ed1ng.\n    B\u00ean c\u1ea1nh t\u00ecnh y\u00eau c\u1ee7a anh d\u00e0nh cho c\u00f4, c\u00f4 c\u0169ng \u0111\u00e3 c\u00f3 m\u1ed9t t\u00ecnh y\u00eau nhi\u1ec7t t\u00ecnh d\u00e0nh cho anh, th\u00f4ng minh, hi\u1ec3u l\u00fd l\u1ebd.....\n","id":"240","is_category_hot":false,"is_category_recommend":false,"is_category_this_week_hot":false,"is_classic":null,"is_classic_action":null,"is_serializing":false,"is_show":true,"last_update":"03-11-2016","link":"http:\/\/cuongtruyen.com\/truyen\/cuong-thu\/240.html","name":"Cu\u1ed3ng Th\u00fa","num":"11","pic":"http:\/\/cuongtruyen.com\/images\/info\/cuong-thu\/240.jpg","updated_at":"2016-11-03T22:08:46+08:00"}}